{
	"class" : {
		"defaultSpec" : "JulienDelplanque 3/26/2016 19:45",
		"help" : "JulienDelplanque 2/7/2016 11:35",
		"icon" : "JulienDelplanque 2/3/2016 14:15" },
	"instance" : {
		"applyAction" : "JulienDelplanque 1/31/2016 15:24",
		"buildClassifier" : "JulienDelplanque 3/30/2016 14:47",
		"downAction" : "JulienDelplanque 2/7/2016 10:57",
		"downShortcut" : "JulienDelplanque 2/24/2016 17:41",
		"enableDisableButtons" : "JulienDelplanque 2/23/2016 19:59",
		"initializeArrows" : "JulienDelplanque 2/25/2016 09:53",
		"initializePresenter" : "JulienDelplanque 3/26/2016 20:19",
		"initializeWidgets" : "JulienDelplanque 3/26/2016 20:22",
		"isReversedCheckbox" : "JulienDelplanque 3/26/2016 19:44",
		"leftListInitialItems" : "JulienDelplanque 3/26/2016 19:47",
		"leftListLabel" : "JulienDelplanque 1/31/2016 15:07",
		"listsChooserLeftLabel" : "JulienDelplanque 2/23/2016 21:32",
		"listsChooserLeftList" : "JulienDelplanque 2/23/2016 21:32",
		"listsChooserRightLabel" : "JulienDelplanque 2/23/2016 21:32",
		"listsChooserRightList" : "JulienDelplanque 2/23/2016 21:32",
		"moveRightListSelectedDown" : "JulienDelplanque 2/24/2016 17:41",
		"moveRightListSelectedUp" : "JulienDelplanque 2/24/2016 17:42",
		"rightListLabel" : "JulienDelplanque 1/31/2016 15:07",
		"title" : "JulienDelplanque 1/31/2016 15:11",
		"upAction" : "JulienDelplanque 2/6/2016 20:55",
		"upShortcut" : "JulienDelplanque 2/24/2016 17:40",
		"updown" : "JulienDelplanque 2/6/2016 19:31" } }
